{
  "openapi": "3.0.3",
  "info": {
    "title": "Mahi (Manta Auth Cache) API",
    "description": "Mahi - Manta Auth Cache. Redis-backed auth cache exposing UFDS-sourced account/user/role/policy lookups plus AWS SigV4/STS/IAM endpoints.",
    "version": "2.1.0"
  },
  "paths": {
    "/account/{account}": {
      "get": {
        "tags": [
          "lookup-deprecated"
        ],
        "summary": "Deprecated alias for `/accounts?login=`.",
        "operationId": "get_account_old",
        "parameters": [
          {
            "in": "path",
            "name": "account",
            "description": "Account login (not uuid).",
            "required": true,
            "schema": {
              "type": "string"
            }
          }
        ],
        "responses": {
          "200": {
            "description": "successful operation",
            "content": {
              "application/json": {
                "schema": {
                  "$ref": "#/components/schemas/AuthInfo"
                }
              }
            }
          },
          "4XX": {
            "$ref": "#/components/responses/Error"
          },
          "5XX": {
            "$ref": "#/components/responses/Error"
          }
        }
      }
    },
    "/accounts": {
      "get": {
        "tags": [
          "lookup"
        ],
        "summary": "Look up an account by login (`?login=` or legacy alias `?account=`).",
        "operationId": "get_account",
        "parameters": [
          {
            "in": "query",
            "name": "login",
            "description": "Account login. Upstream also accepts the historical alias `account=` for the same value.",
            "schema": {
              "nullable": true,
              "type": "string"
            }
          }
        ],
        "responses": {
          "200": {
            "description": "successful operation",
            "content": {
              "application/json": {
                "schema": {
                  "$ref": "#/components/schemas/AuthInfo"
                }
              }
            }
          },
          "4XX": {
            "$ref": "#/components/responses/Error"
          },
          "5XX": {
            "$ref": "#/components/responses/Error"
          }
        }
      }
    },
    "/accounts/{accountid}": {
      "get": {
        "tags": [
          "lookup"
        ],
        "summary": "Look up an account by UUID. Returns `AuthInfo` populated with account",
        "description": "metadata and the account's roles.",
        "operationId": "get_account_by_uuid",
        "parameters": [
          {
            "in": "path",
            "name": "accountid",
            "required": true,
            "schema": {
              "type": "string",
              "format": "uuid"
            }
          }
        ],
        "responses": {
          "200": {
            "description": "successful operation",
            "content": {
              "application/json": {
                "schema": {
                  "$ref": "#/components/schemas/AuthInfo"
                }
              }
            }
          },
          "4XX": {
            "$ref": "#/components/responses/Error"
          },
          "5XX": {
            "$ref": "#/components/responses/Error"
          }
        }
      }
    },
    "/aws-auth/{accesskeyid}": {
      "get": {
        "tags": [
          "aws-sigv4"
        ],
        "summary": "Resolve a principal by AWS access key id. Falls back to UFDS for",
        "description": "MSAR/MSTS temporary credentials.",
        "operationId": "get_user_by_access_key",
        "parameters": [
          {
            "in": "path",
            "name": "accesskeyid",
            "required": true,
            "schema": {
              "type": "string"
            }
          }
        ],
        "responses": {
          "200": {
            "description": "successful operation",
            "content": {
              "application/json": {
                "schema": {
                  "$ref": "#/components/schemas/AwsAuthResult"
                }
              }
            }
          },
          "4XX": {
            "$ref": "#/components/responses/Error"
          },
          "5XX": {
            "$ref": "#/components/responses/Error"
          }
        }
      }
    },
    "/aws-verify": {
      "post": {
        "tags": [
          "aws-sigv4"
        ],
        "summary": "Verify an AWS SigV4 signature over the original client request.",
        "description": "The original method / URL are delivered in the query string. The service implementation must inspect the incoming request's headers directly (via `RequestContext::request`); the request body is opaque here.",
        "operationId": "verify_sig_v4",
        "parameters": [
          {
            "in": "query",
            "name": "method",
            "description": "HTTP method of the original (to-be-verified) request.",
            "required": true,
            "schema": {
              "type": "string"
            }
          },
          {
            "in": "query",
            "name": "url",
            "description": "URL (path + query) of the original (to-be-verified) request.",
            "required": true,
            "schema": {
              "type": "string"
            }
          }
        ],
        "requestBody": {
          "content": {
            "application/json": {
              "schema": {}
            }
          },
          "required": true
        },
        "responses": {
          "200": {
            "description": "successful operation",
            "content": {
              "application/json": {
                "schema": {
                  "$ref": "#/components/schemas/SigV4VerifyResult"
                }
              }
            }
          },
          "4XX": {
            "$ref": "#/components/responses/Error"
          },
          "5XX": {
            "$ref": "#/components/responses/Error"
          }
        }
      }
    },
    "/getName": {
      "post": {
        "tags": [
          "lookup-deprecated"
        ],
        "summary": "Deprecated POST-body variant of `GET /names`.",
        "operationId": "uuid_to_name_old",
        "requestBody": {
          "content": {
            "application/json": {
              "schema": {
                "$ref": "#/components/schemas/UuidToNameBody"
              }
            }
          },
          "required": true
        },
        "responses": {
          "200": {
            "description": "successful operation",
            "content": {
              "application/json": {
                "schema": {
                  "title": "Map_of_String",
                  "type": "object",
                  "additionalProperties": {
                    "type": "string"
                  }
                }
              }
            }
          },
          "4XX": {
            "$ref": "#/components/responses/Error"
          },
          "5XX": {
            "$ref": "#/components/responses/Error"
          }
        }
      }
    },
    "/getUuid": {
      "post": {
        "tags": [
          "lookup-deprecated"
        ],
        "summary": "Deprecated POST-body variant of `GET /uuids`.",
        "operationId": "name_to_uuid_old",
        "requestBody": {
          "content": {
            "application/json": {
              "schema": {
                "$ref": "#/components/schemas/NameToUuidBody"
              }
            }
          },
          "required": true
        },
        "responses": {
          "200": {
            "description": "successful operation",
            "content": {
              "application/json": {
                "schema": {
                  "$ref": "#/components/schemas/NameToUuidResponse"
                }
              }
            }
          },
          "4XX": {
            "$ref": "#/components/responses/Error"
          },
          "5XX": {
            "$ref": "#/components/responses/Error"
          }
        }
      }
    },
    "/iam/create-role": {
      "post": {
        "tags": [
          "iam"
        ],
        "summary": "Create a new IAM role. Writes Redis synchronously, UFDS asynchronously.",
        "description": "Returns 200 (despite the upstream JSDoc claiming 201).",
        "operationId": "iam_create_role",
        "requestBody": {
          "content": {
            "application/json": {
              "schema": {
                "$ref": "#/components/schemas/CreateRoleRequest"
              }
            }
          },
          "required": true
        },
        "responses": {
          "200": {
            "description": "successful operation",
            "content": {
              "application/json": {
                "schema": {
                  "$ref": "#/components/schemas/CreateRoleResponse"
                }
              }
            }
          },
          "4XX": {
            "$ref": "#/components/responses/Error"
          },
          "5XX": {
            "$ref": "#/components/responses/Error"
          }
        }
      }
    },
    "/iam/delete-role/{role_name}": {
      "delete": {
        "tags": [
          "iam"
        ],
        "summary": "Delete a role. Writes Redis synchronously, UFDS asynchronously.",
        "operationId": "iam_delete_role",
        "parameters": [
          {
            "in": "path",
            "name": "role_name",
            "required": true,
            "schema": {
              "type": "string"
            }
          },
          {
            "in": "query",
            "name": "accountUuid",
            "required": true,
            "schema": {
              "type": "string",
              "format": "uuid"
            }
          }
        ],
        "responses": {
          "200": {
            "description": "successful operation",
            "content": {
              "application/json": {
                "schema": {
                  "$ref": "#/components/schemas/DeleteRoleResponse"
                }
              }
            }
          },
          "4XX": {
            "$ref": "#/components/responses/Error"
          },
          "5XX": {
            "$ref": "#/components/responses/Error"
          }
        }
      }
    },
    "/iam/delete-role-policy": {
      "delete": {
        "tags": [
          "iam"
        ],
        "summary": "Detach a policy from a role. All identifiers come from the query",
        "description": "string, not the path (mirrors upstream).",
        "operationId": "iam_delete_role_policy",
        "parameters": [
          {
            "in": "query",
            "name": "accountUuid",
            "required": true,
            "schema": {
              "type": "string",
              "format": "uuid"
            }
          },
          {
            "in": "query",
            "name": "policyName",
            "required": true,
            "schema": {
              "type": "string"
            }
          },
          {
            "in": "query",
            "name": "roleName",
            "required": true,
            "schema": {
              "type": "string"
            }
          }
        ],
        "responses": {
          "200": {
            "description": "successful operation",
            "content": {
              "application/json": {
                "schema": {
                  "$ref": "#/components/schemas/DeleteRolePolicyResponse"
                }
              }
            }
          },
          "4XX": {
            "$ref": "#/components/responses/Error"
          },
          "5XX": {
            "$ref": "#/components/responses/Error"
          }
        }
      }
    },
    "/iam/get-role/{role_name}": {
      "get": {
        "tags": [
          "iam"
        ],
        "summary": "Get a single role by name.",
        "operationId": "iam_get_role",
        "parameters": [
          {
            "in": "path",
            "name": "role_name",
            "required": true,
            "schema": {
              "type": "string"
            }
          },
          {
            "in": "query",
            "name": "accountUuid",
            "required": true,
            "schema": {
              "type": "string",
              "format": "uuid"
            }
          }
        ],
        "responses": {
          "200": {
            "description": "successful operation",
            "content": {
              "application/json": {
                "schema": {
                  "$ref": "#/components/schemas/GetRoleResponse"
                }
              }
            }
          },
          "4XX": {
            "$ref": "#/components/responses/Error"
          },
          "5XX": {
            "$ref": "#/components/responses/Error"
          }
        }
      }
    },
    "/iam/get-role-policy/{role_name}/{policy_name}": {
      "get": {
        "tags": [
          "iam"
        ],
        "summary": "Retrieve a specific role policy document (as a JSON-encoded string).",
        "operationId": "iam_get_role_policy",
        "parameters": [
          {
            "in": "path",
            "name": "policy_name",
            "required": true,
            "schema": {
              "type": "string"
            }
          },
          {
            "in": "path",
            "name": "role_name",
            "required": true,
            "schema": {
              "type": "string"
            }
          },
          {
            "in": "query",
            "name": "accountUuid",
            "required": true,
            "schema": {
              "type": "string",
              "format": "uuid"
            }
          }
        ],
        "responses": {
          "200": {
            "description": "successful operation",
            "content": {
              "application/json": {
                "schema": {
                  "$ref": "#/components/schemas/GetRolePolicyResponse"
                }
              }
            }
          },
          "4XX": {
            "$ref": "#/components/responses/Error"
          },
          "5XX": {
            "$ref": "#/components/responses/Error"
          }
        }
      }
    },
    "/iam/list-role-policies/{role_name}": {
      "get": {
        "tags": [
          "iam"
        ],
        "summary": "List policies attached to a role. Note the lowercase `maxitems` query",
        "description": "parameter (an upstream quirk; `maxItems` is accepted as an alias).",
        "operationId": "iam_list_role_policies",
        "parameters": [
          {
            "in": "path",
            "name": "role_name",
            "required": true,
            "schema": {
              "type": "string"
            }
          },
          {
            "in": "query",
            "name": "accountUuid",
            "required": true,
            "schema": {
              "type": "string",
              "format": "uuid"
            }
          },
          {
            "in": "query",
            "name": "marker",
            "schema": {
              "nullable": true,
              "type": "string"
            }
          },
          {
            "in": "query",
            "name": "maxitems",
            "description": "Maximum number of policy names to return. Upstream is `maxitems` (lowercase) in the handler; this alias accepts the typo-free spelling for forward compatibility.",
            "schema": {
              "nullable": true,
              "type": "integer",
              "format": "uint32",
              "minimum": 0
            }
          }
        ],
        "responses": {
          "200": {
            "description": "successful operation",
            "content": {
              "application/json": {
                "schema": {
                  "$ref": "#/components/schemas/ListRolePoliciesResponse"
                }
              }
            }
          },
          "4XX": {
            "$ref": "#/components/responses/Error"
          },
          "5XX": {
            "$ref": "#/components/responses/Error"
          }
        }
      }
    },
    "/iam/list-roles": {
      "get": {
        "tags": [
          "iam"
        ],
        "summary": "List roles within an account.",
        "operationId": "iam_list_roles",
        "parameters": [
          {
            "in": "query",
            "name": "accountUuid",
            "required": true,
            "schema": {
              "type": "string",
              "format": "uuid"
            }
          },
          {
            "in": "query",
            "name": "marker",
            "schema": {
              "nullable": true,
              "type": "string"
            }
          },
          {
            "in": "query",
            "name": "maxItems",
            "description": "Upstream default is 100; server caps at 1000.",
            "schema": {
              "nullable": true,
              "type": "integer",
              "format": "uint32",
              "minimum": 0
            }
          },
          {
            "in": "query",
            "name": "startingToken",
            "description": "Alternate name accepted by upstream (`?startingToken=`).",
            "schema": {
              "nullable": true,
              "type": "string"
            }
          }
        ],
        "responses": {
          "200": {
            "description": "successful operation",
            "content": {
              "application/json": {
                "schema": {
                  "$ref": "#/components/schemas/ListRolesResponse"
                }
              }
            }
          },
          "4XX": {
            "$ref": "#/components/responses/Error"
          },
          "5XX": {
            "$ref": "#/components/responses/Error"
          }
        }
      }
    },
    "/iam/put-role-policy": {
      "post": {
        "tags": [
          "iam"
        ],
        "summary": "Attach a policy to a role.",
        "operationId": "iam_put_role_policy",
        "requestBody": {
          "content": {
            "application/json": {
              "schema": {
                "$ref": "#/components/schemas/PutRolePolicyRequest"
              }
            }
          },
          "required": true
        },
        "responses": {
          "200": {
            "description": "successful operation",
            "content": {
              "application/json": {
                "schema": {
                  "$ref": "#/components/schemas/PutRolePolicyResponse"
                }
              }
            }
          },
          "4XX": {
            "$ref": "#/components/responses/Error"
          },
          "5XX": {
            "$ref": "#/components/responses/Error"
          }
        }
      }
    },
    "/lookup": {
      "get": {
        "tags": [
          "lookup"
        ],
        "summary": "Bulk lookup of all known accounts. Response is a map keyed by account",
        "description": "UUID, not an array.",
        "operationId": "lookup",
        "responses": {
          "200": {
            "description": "successful operation",
            "content": {
              "application/json": {
                "schema": {
                  "title": "Map_of_LookupEntry",
                  "type": "object",
                  "additionalProperties": {
                    "$ref": "#/components/schemas/LookupEntry"
                  }
                }
              }
            }
          },
          "4XX": {
            "$ref": "#/components/responses/Error"
          },
          "5XX": {
            "$ref": "#/components/responses/Error"
          }
        }
      }
    },
    "/names": {
      "get": {
        "tags": [
          "lookup"
        ],
        "summary": "Resolve a set of UUIDs to their names/logins. The response is a map",
        "description": "keyed by UUID, not an array.",
        "operationId": "uuid_to_name",
        "parameters": [
          {
            "in": "query",
            "name": "uuid",
            "description": "Comma-separated list of UUIDs to resolve.",
            "schema": {
              "nullable": true,
              "type": "string"
            }
          }
        ],
        "responses": {
          "200": {
            "description": "successful operation",
            "content": {
              "application/json": {
                "schema": {
                  "title": "Map_of_String",
                  "type": "object",
                  "additionalProperties": {
                    "type": "string"
                  }
                }
              }
            }
          },
          "4XX": {
            "$ref": "#/components/responses/Error"
          },
          "5XX": {
            "$ref": "#/components/responses/Error"
          }
        }
      }
    },
    "/ping": {
      "get": {
        "tags": [
          "lookup"
        ],
        "summary": "Health check. Returns 204 on success; 503 if Redis is unavailable or",
        "description": "the replicator is not caught up.",
        "operationId": "ping",
        "responses": {
          "204": {
            "description": "resource updated"
          },
          "4XX": {
            "$ref": "#/components/responses/Error"
          },
          "5XX": {
            "$ref": "#/components/responses/Error"
          }
        }
      }
    },
    "/roles": {
      "get": {
        "tags": [
          "lookup"
        ],
        "summary": "List members of a role identified by `(account, role-name)`. The",
        "description": "returned `AuthInfo.role` field is populated for this endpoint.",
        "operationId": "get_role_members",
        "parameters": [
          {
            "in": "query",
            "name": "account",
            "required": true,
            "schema": {
              "type": "string"
            }
          },
          {
            "in": "query",
            "name": "role",
            "description": "Role name. Upstream also accepts the alias `name=`.",
            "schema": {
              "nullable": true,
              "type": "string"
            }
          }
        ],
        "responses": {
          "200": {
            "description": "successful operation",
            "content": {
              "application/json": {
                "schema": {
                  "$ref": "#/components/schemas/AuthInfo"
                }
              }
            }
          },
          "4XX": {
            "$ref": "#/components/responses/Error"
          },
          "5XX": {
            "$ref": "#/components/responses/Error"
          }
        }
      }
    },
    "/sts/assume-role": {
      "post": {
        "tags": [
          "sts"
        ],
        "summary": "Mint MSAR-prefixed temporary credentials after validating the trust",
        "description": "policy of the target role.",
        "operationId": "sts_assume_role",
        "requestBody": {
          "content": {
            "application/json": {
              "schema": {
                "$ref": "#/components/schemas/AssumeRoleRequest"
              }
            }
          },
          "required": true
        },
        "responses": {
          "200": {
            "description": "successful operation",
            "content": {
              "application/json": {
                "schema": {
                  "$ref": "#/components/schemas/AssumeRoleResponse"
                }
              }
            }
          },
          "4XX": {
            "$ref": "#/components/responses/Error"
          },
          "5XX": {
            "$ref": "#/components/responses/Error"
          }
        }
      }
    },
    "/sts/get-caller-identity": {
      "post": {
        "tags": [
          "sts"
        ],
        "summary": "Return caller-identity information. The wire response is XML with",
        "description": "`Content-Type: text/xml`, so this endpoint uses `Response<Body>` and relies on a Phase-2b OpenAPI spec patch to declare the correct content type and a `string` schema.",
        "operationId": "sts_get_caller_identity",
        "requestBody": {
          "content": {
            "application/json": {
              "schema": {
                "$ref": "#/components/schemas/GetCallerIdentityRequest"
              }
            }
          },
          "required": true
        },
        "responses": {
          "default": {
            "description": "",
            "content": {
              "*/*": {
                "schema": {}
              }
            }
          }
        }
      }
    },
    "/sts/get-session-token": {
      "post": {
        "tags": [
          "sts"
        ],
        "summary": "Mint MSTS-prefixed temporary credentials for the caller.",
        "operationId": "sts_get_session_token",
        "requestBody": {
          "content": {
            "application/json": {
              "schema": {
                "$ref": "#/components/schemas/GetSessionTokenRequest"
              }
            }
          },
          "required": true
        },
        "responses": {
          "200": {
            "description": "successful operation",
            "content": {
              "application/json": {
                "schema": {
                  "$ref": "#/components/schemas/GetSessionTokenResponse"
                }
              }
            }
          },
          "4XX": {
            "$ref": "#/components/responses/Error"
          },
          "5XX": {
            "$ref": "#/components/responses/Error"
          }
        }
      }
    },
    "/user/{account}/{user}": {
      "get": {
        "tags": [
          "lookup-deprecated"
        ],
        "summary": "Deprecated alias for `/users?account=&login=`.",
        "operationId": "get_user_old",
        "parameters": [
          {
            "in": "path",
            "name": "account",
            "description": "Account login.",
            "required": true,
            "schema": {
              "type": "string"
            }
          },
          {
            "in": "path",
            "name": "user",
            "description": "Sub-user login.",
            "required": true,
            "schema": {
              "type": "string"
            }
          }
        ],
        "responses": {
          "200": {
            "description": "successful operation",
            "content": {
              "application/json": {
                "schema": {
                  "$ref": "#/components/schemas/AuthInfo"
                }
              }
            }
          },
          "4XX": {
            "$ref": "#/components/responses/Error"
          },
          "5XX": {
            "$ref": "#/components/responses/Error"
          }
        }
      }
    },
    "/users": {
      "get": {
        "tags": [
          "lookup"
        ],
        "summary": "Look up a sub-user by (account-login, sub-user-login).",
        "description": "When `fallback=true` (the upstream default) and the sub-user is missing, the handler returns the account-only `AuthInfo` with `user=None` and an empty `roles` map.",
        "operationId": "get_user",
        "parameters": [
          {
            "in": "query",
            "name": "account",
            "description": "Account login.",
            "required": true,
            "schema": {
              "type": "string"
            }
          },
          {
            "in": "query",
            "name": "fallback",
            "description": "When `true`, missing sub-users are swallowed and the account-only `AuthInfo` (no `user`, empty `roles`) is returned with HTTP 200. Defaults to `true` upstream. Accepts boolean `true`/`false` or the strings `\"true\"`/`\"false\"`.",
            "schema": {
              "nullable": true,
              "type": "boolean"
            }
          },
          {
            "in": "query",
            "name": "login",
            "description": "Sub-user login.",
            "required": true,
            "schema": {
              "type": "string"
            }
          }
        ],
        "responses": {
          "200": {
            "description": "successful operation",
            "content": {
              "application/json": {
                "schema": {
                  "$ref": "#/components/schemas/AuthInfo"
                }
              }
            }
          },
          "4XX": {
            "$ref": "#/components/responses/Error"
          },
          "5XX": {
            "$ref": "#/components/responses/Error"
          }
        }
      }
    },
    "/users/{userid}": {
      "get": {
        "tags": [
          "lookup"
        ],
        "summary": "Look up a sub-user by UUID. Also loads the owning account.",
        "operationId": "get_user_by_uuid",
        "parameters": [
          {
            "in": "path",
            "name": "userid",
            "required": true,
            "schema": {
              "type": "string",
              "format": "uuid"
            }
          }
        ],
        "responses": {
          "200": {
            "description": "successful operation",
            "content": {
              "application/json": {
                "schema": {
                  "$ref": "#/components/schemas/AuthInfo"
                }
              }
            }
          },
          "4XX": {
            "$ref": "#/components/responses/Error"
          },
          "5XX": {
            "$ref": "#/components/responses/Error"
          }
        }
      }
    },
    "/uuids": {
      "get": {
        "tags": [
          "lookup"
        ],
        "summary": "Resolve a set of names to their UUIDs within an account. Returns",
        "description": "`{account}` alone when no `name=` query is supplied.",
        "operationId": "name_to_uuid",
        "parameters": [
          {
            "in": "query",
            "name": "account",
            "required": true,
            "schema": {
              "type": "string"
            }
          },
          {
            "in": "query",
            "name": "name",
            "description": "Comma-separated list of names, or `None` for \"no names\".",
            "schema": {
              "nullable": true,
              "type": "string"
            }
          },
          {
            "in": "query",
            "name": "type",
            "description": "Type of object to look up.",
            "required": true,
            "schema": {
              "$ref": "#/components/schemas/ObjectType"
            }
          }
        ],
        "responses": {
          "200": {
            "description": "successful operation",
            "content": {
              "application/json": {
                "schema": {
                  "$ref": "#/components/schemas/NameToUuidResponse"
                }
              }
            }
          },
          "4XX": {
            "$ref": "#/components/responses/Error"
          },
          "5XX": {
            "$ref": "#/components/responses/Error"
          }
        }
      }
    }
  },
  "components": {
    "schemas": {
      "AccessKeySecret": {
        "description": "Secret material stored alongside an access key id.\n\nLives under `user.accesskeys[keyId]`. For temporary credentials, the `sessionToken`, `expiration`, `principalUuid`, and `assumedRole` fields are populated; for permanent credentials only `secret` and `type` are present.",
        "type": "object",
        "properties": {
          "assumedRole": {
            "nullable": true,
            "description": "Assumed-role metadata for MSAR-prefixed temporary credentials."
          },
          "expiration": {
            "nullable": true,
            "description": "Expiration timestamp (ISO8601) for temporary credentials.",
            "type": "string"
          },
          "principalUuid": {
            "nullable": true,
            "description": "Uuid of the principal (user) the temporary credential belongs to.",
            "type": "string",
            "format": "uuid"
          },
          "secret": {
            "description": "Secret access key (base64).",
            "type": "string"
          },
          "sessionToken": {
            "nullable": true,
            "description": "Opaque session-token blob returned to clients using STS credentials.",
            "type": "string"
          },
          "type": {
            "$ref": "#/components/schemas/CredentialType"
          }
        },
        "required": [
          "secret",
          "type"
        ]
      },
      "Account": {
        "description": "Redis-backed account blob (UFDS passthrough).\n\nThe concrete set of fields on accounts varies by deployment and UFDS schema. We model the commonly-observed fields explicitly and capture any extras via `#[serde(flatten)]` into a catch-all map.",
        "type": "object",
        "properties": {
          "address": {
            "nullable": true,
            "type": "string"
          },
          "approved_for_provisioning": {
            "nullable": true,
            "type": "boolean"
          },
          "city": {
            "nullable": true,
            "type": "string"
          },
          "cn": {
            "nullable": true,
            "type": "string"
          },
          "company": {
            "nullable": true,
            "type": "string"
          },
          "country": {
            "nullable": true,
            "type": "string"
          },
          "email": {
            "nullable": true,
            "type": "string"
          },
          "given_name": {
            "nullable": true,
            "type": "string"
          },
          "groups": {
            "nullable": true,
            "type": "array",
            "items": {
              "type": "string"
            }
          },
          "isOperator": {
            "nullable": true,
            "description": "Set by `redislib.getAccount`. Camel-cased on the wire (UFDS bool).",
            "type": "boolean"
          },
          "key_info": {
            "nullable": true,
            "description": "Per-fingerprint attestation metadata (`attested`, `pin`, `touch`) replicated from UFDS `sdckey` entries. Keyed by the same fingerprint as `keys`.",
            "type": "object",
            "additionalProperties": true
          },
          "keys": {
            "nullable": true,
            "description": "Key fingerprints -> key blobs. Shape is deployment-specific.",
            "type": "object",
            "additionalProperties": true
          },
          "login": {
            "type": "string"
          },
          "phone": {
            "nullable": true,
            "type": "string"
          },
          "postal_code": {
            "nullable": true,
            "type": "string"
          },
          "roles": {
            "nullable": true,
            "description": "Role uuids attached at the account level.",
            "type": "array",
            "items": {
              "type": "string",
              "format": "uuid"
            }
          },
          "s": {
            "nullable": true,
            "type": "string"
          },
          "sn": {
            "nullable": true,
            "type": "string"
          },
          "state": {
            "nullable": true,
            "type": "string"
          },
          "triton_cns_enabled": {
            "nullable": true,
            "type": "boolean"
          },
          "type": {
            "$ref": "#/components/schemas/ObjectTypeTag"
          },
          "uuid": {
            "type": "string",
            "format": "uuid"
          }
        },
        "required": [
          "login",
          "type",
          "uuid"
        ],
        "additionalProperties": true
      },
      "AssumeRoleRequest": {
        "description": "Request body for `POST /sts/assume-role`.",
        "type": "object",
        "properties": {
          "DurationSeconds": {
            "nullable": true,
            "description": "Desired lifetime in seconds. Upstream validates the range 900..=43200.",
            "type": "integer",
            "format": "uint64",
            "minimum": 0
          },
          "RoleArn": {
            "type": "string"
          },
          "RoleSessionName": {
            "type": "string"
          },
          "caller": {
            "$ref": "#/components/schemas/Caller"
          }
        },
        "required": [
          "RoleArn",
          "RoleSessionName",
          "caller"
        ]
      },
      "AssumeRoleResponse": {
        "description": "Outer response envelope returned by `POST /sts/assume-role`.\n\nMahi emulates AWS's XML envelope with a JSON object of the same shape, so callers must navigate two nested `AssumeRoleResponse` / `AssumeRoleResult` keys.",
        "type": "object",
        "properties": {
          "AssumeRoleResponse": {
            "$ref": "#/components/schemas/AssumeRoleResponseInner"
          }
        },
        "required": [
          "AssumeRoleResponse"
        ]
      },
      "AssumeRoleResponseInner": {
        "description": "Middle envelope wrapping the result.",
        "type": "object",
        "properties": {
          "AssumeRoleResult": {
            "$ref": "#/components/schemas/AssumeRoleResult"
          }
        },
        "required": [
          "AssumeRoleResult"
        ]
      },
      "AssumeRoleResult": {
        "description": "Inner `AssumeRoleResult` object.",
        "type": "object",
        "properties": {
          "AssumedRoleUser": {
            "$ref": "#/components/schemas/AssumedRoleUser"
          },
          "Credentials": {
            "$ref": "#/components/schemas/StsCredentials"
          }
        },
        "required": [
          "AssumedRoleUser",
          "Credentials"
        ]
      },
      "AssumedRole": {
        "description": "Assumed-role context attached to temporary credentials.",
        "type": "object",
        "properties": {
          "arn": {
            "type": "string"
          },
          "policies": {
            "nullable": true,
            "type": "array",
            "items": {
              "$ref": "#/components/schemas/PolicyEntry"
            }
          },
          "roleUuid": {
            "nullable": true,
            "type": "string",
            "format": "uuid"
          },
          "sessionName": {
            "nullable": true,
            "type": "string"
          }
        },
        "required": [
          "arn"
        ]
      },
      "AssumedRoleUser": {
        "description": "Assumed-role principal returned by `AssumeRole`.",
        "type": "object",
        "properties": {
          "Arn": {
            "type": "string"
          },
          "AssumedRoleId": {
            "type": "string"
          }
        },
        "required": [
          "Arn",
          "AssumedRoleId"
        ]
      },
      "AuthInfo": {
        "description": "Auth payload returned by most lookup endpoints.\n\nMahi builds this up progressively as `req.auth` and sends it back verbatim. `user` is optional because several routes (and the `fallback=true` branch of `GET /users`) only populate `account` + `roles`. `role` is only populated by `GET /roles`.",
        "type": "object",
        "properties": {
          "account": {
            "$ref": "#/components/schemas/Account"
          },
          "role": {
            "nullable": true,
            "description": "Single role populated only by `GET /roles`.",
            "allOf": [
              {
                "$ref": "#/components/schemas/Role"
              }
            ]
          },
          "roles": {
            "description": "Roles map keyed by role uuid.",
            "default": {},
            "type": "object",
            "additionalProperties": {
              "$ref": "#/components/schemas/Role"
            }
          },
          "user": {
            "nullable": true,
            "allOf": [
              {
                "$ref": "#/components/schemas/User"
              }
            ]
          }
        },
        "required": [
          "account"
        ]
      },
      "AwsAuthResult": {
        "description": "Result of `GET /aws-auth/:accesskeyid`.\n\nContains the full principal context plus, when applicable, assumed-role / temporary-credential metadata.",
        "type": "object",
        "properties": {
          "account": {
            "$ref": "#/components/schemas/Account"
          },
          "assumedRole": {
            "nullable": true,
            "allOf": [
              {
                "$ref": "#/components/schemas/AssumedRole"
              }
            ]
          },
          "isTemporaryCredential": {
            "nullable": true,
            "type": "boolean"
          },
          "roles": {
            "default": {},
            "type": "object",
            "additionalProperties": {
              "$ref": "#/components/schemas/Role"
            }
          },
          "sessionName": {
            "nullable": true,
            "type": "string"
          },
          "user": {
            "nullable": true,
            "allOf": [
              {
                "$ref": "#/components/schemas/User"
              }
            ]
          }
        },
        "required": [
          "account"
        ]
      },
      "Caller": {
        "description": "The `caller` object every STS endpoint expects in its body.",
        "type": "object",
        "properties": {
          "account": {
            "$ref": "#/components/schemas/CallerAccount"
          },
          "user": {
            "nullable": true,
            "allOf": [
              {
                "$ref": "#/components/schemas/CallerUser"
              }
            ]
          }
        },
        "required": [
          "account"
        ]
      },
      "CallerAccount": {
        "description": "Account identifier attached to STS calls.",
        "type": "object",
        "properties": {
          "email": {
            "nullable": true,
            "type": "string"
          },
          "login": {
            "type": "string"
          },
          "uuid": {
            "type": "string",
            "format": "uuid"
          }
        },
        "required": [
          "login",
          "uuid"
        ],
        "additionalProperties": true
      },
      "CallerUser": {
        "description": "Optional sub-user identifier attached to STS calls.",
        "type": "object",
        "properties": {
          "email": {
            "nullable": true,
            "type": "string"
          },
          "login": {
            "type": "string"
          },
          "uuid": {
            "type": "string",
            "format": "uuid"
          }
        },
        "required": [
          "login",
          "uuid"
        ],
        "additionalProperties": true
      },
      "CreateRoleRequest": {
        "description": "Request body for `POST /iam/create-role`.",
        "type": "object",
        "properties": {
          "accountUuid": {
            "type": "string",
            "format": "uuid"
          },
          "assumeRolePolicyDocument": {
            "nullable": true,
            "description": "Trust policy document (JSON-encoded string).",
            "type": "string"
          },
          "description": {
            "nullable": true,
            "type": "string"
          },
          "path": {
            "nullable": true,
            "description": "IAM path. Upstream defaults to `\"/\"` when absent.",
            "type": "string"
          },
          "roleName": {
            "type": "string"
          }
        },
        "required": [
          "accountUuid",
          "roleName"
        ]
      },
      "CreateRoleResponse": {
        "description": "Response for `POST /iam/create-role`.",
        "type": "object",
        "properties": {
          "Role": {
            "$ref": "#/components/schemas/IamRole"
          }
        },
        "required": [
          "Role"
        ]
      },
      "CredentialType": {
        "description": "Credential type for access keys.\n\nWire format values are `\"permanent\"` and `\"temporary\"`. Temporary credentials are produced by the STS endpoints (MSAR/MSTS prefixes).",
        "oneOf": [
          {
            "type": "string",
            "enum": [
              "permanent",
              "temporary"
            ]
          },
          {
            "description": "Catch-all for credential types added after this client was compiled.",
            "type": "string",
            "enum": [
              "unknown"
            ]
          }
        ]
      },
      "DeleteRolePolicyResponse": {
        "description": "Response for `DEL /iam/delete-role-policy`.",
        "type": "object",
        "properties": {
          "message": {
            "type": "string"
          },
          "policyName": {
            "type": "string"
          },
          "roleName": {
            "type": "string"
          }
        },
        "required": [
          "message",
          "policyName",
          "roleName"
        ]
      },
      "DeleteRoleResponse": {
        "description": "Response for `DEL /iam/delete-role/{roleName}`.",
        "type": "object",
        "properties": {
          "message": {
            "type": "string"
          },
          "roleName": {
            "type": "string"
          }
        },
        "required": [
          "message",
          "roleName"
        ]
      },
      "Error": {
        "description": "Error information from a response.",
        "type": "object",
        "properties": {
          "error_code": {
            "type": "string"
          },
          "message": {
            "type": "string"
          },
          "request_id": {
            "type": "string"
          }
        },
        "required": [
          "message",
          "request_id"
        ]
      },
      "GetCallerIdentityRequest": {
        "description": "Request body for `POST /sts/get-caller-identity`.\n\nThe response is emitted as raw XML with `Content-Type: text/xml`; the trait therefore uses `Result<Response<Body>, HttpError>` for this endpoint and a Phase-2b spec patch reshapes the response schema accordingly.",
        "type": "object",
        "properties": {
          "caller": {
            "$ref": "#/components/schemas/Caller"
          }
        },
        "required": [
          "caller"
        ]
      },
      "GetRolePolicyResponse": {
        "description": "Response for `GET /iam/get-role-policy/{roleName}/{policyName}`.",
        "type": "object",
        "properties": {
          "PolicyDocument": {
            "description": "Policy document (JSON string).",
            "type": "string"
          },
          "PolicyName": {
            "type": "string"
          },
          "RoleName": {
            "type": "string"
          }
        },
        "required": [
          "PolicyDocument",
          "PolicyName",
          "RoleName"
        ]
      },
      "GetRoleResponse": {
        "description": "Response for `GET /iam/get-role/{roleName}`.",
        "type": "object",
        "properties": {
          "Role": {
            "$ref": "#/components/schemas/IamRole"
          }
        },
        "required": [
          "Role"
        ]
      },
      "GetSessionTokenRequest": {
        "description": "Request body for `POST /sts/get-session-token`.",
        "type": "object",
        "properties": {
          "DurationSeconds": {
            "nullable": true,
            "description": "Desired lifetime in seconds. Upstream validates 900..=129600.",
            "type": "integer",
            "format": "uint64",
            "minimum": 0
          },
          "caller": {
            "$ref": "#/components/schemas/Caller"
          }
        },
        "required": [
          "caller"
        ]
      },
      "GetSessionTokenResponse": {
        "description": "Outer response envelope for `POST /sts/get-session-token`.",
        "type": "object",
        "properties": {
          "GetSessionTokenResponse": {
            "$ref": "#/components/schemas/GetSessionTokenResponseInner"
          }
        },
        "required": [
          "GetSessionTokenResponse"
        ]
      },
      "GetSessionTokenResponseInner": {
        "description": "Middle envelope wrapping the result.",
        "type": "object",
        "properties": {
          "GetSessionTokenResult": {
            "$ref": "#/components/schemas/GetSessionTokenResult"
          }
        },
        "required": [
          "GetSessionTokenResult"
        ]
      },
      "GetSessionTokenResult": {
        "description": "Inner `GetSessionTokenResult` object.",
        "type": "object",
        "properties": {
          "Credentials": {
            "$ref": "#/components/schemas/StsCredentials"
          }
        },
        "required": [
          "Credentials"
        ]
      },
      "IamRole": {
        "description": "IAM role object (PascalCase on the wire).",
        "type": "object",
        "properties": {
          "Arn": {
            "type": "string"
          },
          "AssumeRolePolicyDocument": {
            "description": "JSON-stringified trust policy document.",
            "type": "string"
          },
          "CreateDate": {
            "description": "RFC3339 create date.",
            "type": "string"
          },
          "Description": {
            "nullable": true,
            "type": "string"
          },
          "MaxSessionDuration": {
            "nullable": true,
            "type": "integer",
            "format": "uint32",
            "minimum": 0
          },
          "Path": {
            "description": "IAM path (default `\"/\"`).",
            "type": "string"
          },
          "RoleId": {
            "type": "string",
            "format": "uuid"
          },
          "RoleName": {
            "type": "string"
          }
        },
        "required": [
          "Arn",
          "AssumeRolePolicyDocument",
          "CreateDate",
          "Path",
          "RoleId",
          "RoleName"
        ]
      },
      "ListRolePoliciesResponse": {
        "description": "Response for `GET /iam/list-role-policies/{roleName}`.",
        "type": "object",
        "properties": {
          "IsTruncated": {
            "type": "boolean"
          },
          "Marker": {
            "nullable": true,
            "type": "string"
          },
          "PolicyNames": {
            "type": "array",
            "items": {
              "type": "string"
            }
          }
        },
        "required": [
          "IsTruncated",
          "PolicyNames"
        ]
      },
      "ListRolesResponse": {
        "description": "Response for `GET /iam/list-roles`.\n\n**Mixed casing** at the top level: `roles` is lowercase, `IsTruncated` and `Marker` are PascalCase. Apply field-level renames rather than a struct `rename_all`.",
        "type": "object",
        "properties": {
          "IsTruncated": {
            "type": "boolean"
          },
          "Marker": {
            "nullable": true,
            "type": "string"
          },
          "roles": {
            "description": "Lowercase on the wire.",
            "type": "array",
            "items": {
              "$ref": "#/components/schemas/IamRole"
            }
          }
        },
        "required": [
          "IsTruncated",
          "roles"
        ]
      },
      "LookupEntry": {
        "description": "Entry value for `GET /lookup` responses (map keyed by account uuid).",
        "type": "object",
        "properties": {
          "approved": {
            "type": "boolean"
          },
          "login": {
            "type": "string"
          }
        },
        "required": [
          "approved",
          "login"
        ]
      },
      "MantaPolicy": {
        "description": "Mahi-native policy payload attached to a role via `PutRolePolicy`.",
        "type": "object",
        "properties": {
          "id": {
            "type": "string",
            "format": "uuid"
          },
          "name": {
            "type": "string"
          },
          "rules": {
            "description": "Aperture rule strings.",
            "type": "array",
            "items": {
              "type": "string"
            }
          }
        },
        "required": [
          "id",
          "name",
          "rules"
        ]
      },
      "NameToUuidBody": {
        "description": "Body of the deprecated `POST /getUuid`.",
        "type": "object",
        "properties": {
          "account": {
            "type": "string"
          },
          "name": {
            "nullable": true,
            "description": "Single name or array of names.",
            "default": null,
            "allOf": [
              {
                "$ref": "#/components/schemas/StringOrVec"
              }
            ]
          },
          "type": {
            "$ref": "#/components/schemas/ObjectType"
          }
        },
        "required": [
          "account",
          "type"
        ]
      },
      "NameToUuidResponse": {
        "description": "Response for `GET /uuids` and `POST /getUuid`.\n\nWhen no `name=` was supplied, only `account` is populated. Otherwise `uuids` contains a map of `name -> uuid` for each requested name.",
        "type": "object",
        "properties": {
          "account": {
            "type": "string",
            "format": "uuid"
          },
          "uuids": {
            "nullable": true,
            "type": "object",
            "additionalProperties": {
              "type": "string",
              "format": "uuid"
            }
          }
        },
        "required": [
          "account"
        ]
      },
      "ObjectType": {
        "description": "Object types accepted by `GET /uuids?type=`.\n\nThe set is asserted in upstream `redislib.getUuid` and is lowercase on the wire.",
        "type": "string",
        "enum": [
          "role",
          "user",
          "policy"
        ]
      },
      "ObjectTypeTag": {
        "description": "Internal `type` field stored on every Redis blob. Mahi may grow additional object types over time, so include a catch-all `Unknown` variant.",
        "oneOf": [
          {
            "type": "string",
            "enum": [
              "account",
              "user",
              "role",
              "policy",
              "accesskey"
            ]
          },
          {
            "description": "Catch-all for object types added after this client was compiled.",
            "type": "string",
            "enum": [
              "unknown"
            ]
          }
        ]
      },
      "PolicyEntry": {
        "description": "Policy entry attached to an assumed role.",
        "type": "object",
        "properties": {
          "name": {
            "nullable": true,
            "type": "string"
          },
          "rules": {
            "nullable": true,
            "type": "array",
            "items": {
              "type": "string"
            }
          },
          "uuid": {
            "nullable": true,
            "type": "string",
            "format": "uuid"
          }
        }
      },
      "PutRolePolicyRequest": {
        "description": "Request body for `POST /iam/put-role-policy`.",
        "type": "object",
        "properties": {
          "accountUuid": {
            "type": "string",
            "format": "uuid"
          },
          "mantaPolicy": {
            "description": "Mahi-native policy object stored under `/policy/:id`.",
            "allOf": [
              {
                "$ref": "#/components/schemas/MantaPolicy"
              }
            ]
          },
          "policyDocument": {
            "description": "Raw IAM policy document (JSON string).",
            "type": "string"
          },
          "policyName": {
            "type": "string"
          },
          "roleName": {
            "type": "string"
          }
        },
        "required": [
          "accountUuid",
          "mantaPolicy",
          "policyDocument",
          "policyName",
          "roleName"
        ]
      },
      "PutRolePolicyResponse": {
        "description": "Response for `POST /iam/put-role-policy`.",
        "type": "object",
        "properties": {
          "message": {
            "type": "string"
          },
          "policyName": {
            "type": "string"
          },
          "roleName": {
            "type": "string"
          }
        },
        "required": [
          "message",
          "policyName",
          "roleName"
        ]
      },
      "Role": {
        "description": "Redis-backed role blob.",
        "type": "object",
        "properties": {
          "account": {
            "description": "Owning account uuid.",
            "type": "string",
            "format": "uuid"
          },
          "assumerolepolicydocument": {
            "nullable": true,
            "description": "STS assume-role policy document (JSON string).",
            "type": "string"
          },
          "createtime": {
            "nullable": true,
            "description": "RFC3339/UFDS create timestamp.",
            "type": "string"
          },
          "description": {
            "nullable": true,
            "type": "string"
          },
          "members": {
            "nullable": true,
            "type": "array",
            "items": {}
          },
          "name": {
            "type": "string"
          },
          "path": {
            "nullable": true,
            "description": "IAM path (default `\"/\"`).",
            "type": "string"
          },
          "permissionPolicies": {
            "nullable": true,
            "description": "Policy metadata attached for STS evaluation. Shape is internal. Wire name is camelCase (`permissionPolicies`); it is the only camelCase field on this otherwise-lowercase Redis blob."
          },
          "policies": {
            "description": "Policy uuids attached to this role.",
            "default": [],
            "type": "array",
            "items": {
              "type": "string",
              "format": "uuid"
            }
          },
          "rules": {
            "nullable": true,
            "description": "Inline rules (aperture policy expressions).",
            "type": "array",
            "items": {
              "type": "string"
            }
          },
          "type": {
            "$ref": "#/components/schemas/ObjectTypeTag"
          },
          "uuid": {
            "type": "string",
            "format": "uuid"
          }
        },
        "required": [
          "account",
          "name",
          "type",
          "uuid"
        ],
        "additionalProperties": true
      },
      "SigV4VerifyResult": {
        "description": "Result of `POST /aws-verify` on a valid signature.\n\nThe handler always responds with `valid: true` on success (invalid signatures come back as HTTP errors).",
        "type": "object",
        "properties": {
          "accessKeyId": {
            "type": "string"
          },
          "assumedRole": {
            "nullable": true,
            "description": "Assumed-role metadata (present only for MSAR temporary credentials)."
          },
          "isTemporaryCredential": {
            "nullable": true,
            "type": "boolean"
          },
          "principalUuid": {
            "nullable": true,
            "description": "Principal uuid for temporary credentials.",
            "type": "string",
            "format": "uuid"
          },
          "signingKey": {
            "nullable": true,
            "description": "Derived signing key. Upstream JSON-encodes a Node `Buffer`, so the on-the-wire shape is `{\"type\":\"Buffer\",\"data\":[...]}`. Phase 5 should confirm whether any caller actually consumes this; we keep it opaque for now."
          },
          "userUuid": {
            "type": "string",
            "format": "uuid"
          },
          "valid": {
            "type": "boolean"
          }
        },
        "required": [
          "accessKeyId",
          "userUuid",
          "valid"
        ]
      },
      "StringOrVec": {
        "description": "Accepts either a single value or a JSON array of values (both forms are used by the deprecated `POST /getUuid` and `POST /getName` endpoints).",
        "anyOf": [
          {
            "type": "string"
          },
          {
            "type": "array",
            "items": {
              "type": "string"
            }
          }
        ]
      },
      "StsCredentials": {
        "description": "Temporary credentials returned by `AssumeRole` and `GetSessionToken`.",
        "type": "object",
        "properties": {
          "AccessKeyId": {
            "type": "string"
          },
          "Expiration": {
            "description": "RFC3339/ISO8601 expiration timestamp.",
            "type": "string"
          },
          "SecretAccessKey": {
            "type": "string"
          },
          "SessionToken": {
            "type": "string"
          }
        },
        "required": [
          "AccessKeyId",
          "Expiration",
          "SecretAccessKey",
          "SessionToken"
        ]
      },
      "User": {
        "description": "Redis-backed sub-user blob.",
        "type": "object",
        "properties": {
          "accesskeys": {
            "nullable": true,
            "description": "Access keys keyed by access-key id. Values contain secret material.",
            "type": "object",
            "additionalProperties": {
              "$ref": "#/components/schemas/AccessKeySecret"
            }
          },
          "account": {
            "description": "Owning account uuid.",
            "type": "string",
            "format": "uuid"
          },
          "cn": {
            "nullable": true,
            "type": "string"
          },
          "company": {
            "nullable": true,
            "type": "string"
          },
          "email": {
            "nullable": true,
            "type": "string"
          },
          "given_name": {
            "nullable": true,
            "type": "string"
          },
          "key_info": {
            "nullable": true,
            "description": "Per-fingerprint attestation metadata (`attested`, `pin`, `touch`) replicated from UFDS `sdckey` entries. Keyed by the same fingerprint as `keys`.",
            "type": "object",
            "additionalProperties": true
          },
          "keys": {
            "nullable": true,
            "description": "SSH public-key fingerprints -> key blobs, replicated from UFDS `sdckey` entries attached to the sub-user. Shape mirrors [`Account::keys`]: the blob is deployment-specific (PEM SubjectPublicKeyInfo on the Triton deployments we've seen, `ssh-rsa AAAA...` on some others) and verifiers should parse both.\n\nMust be modeled explicitly here — if it lived only in `#[serde(flatten)] extra`, Progenitor's regenerated client type would silently drop it at the wire boundary, since the generated client has no catch-all.",
            "type": "object",
            "additionalProperties": true
          },
          "login": {
            "type": "string"
          },
          "roles": {
            "nullable": true,
            "description": "Role uuids attached at the user level.",
            "type": "array",
            "items": {
              "type": "string",
              "format": "uuid"
            }
          },
          "s": {
            "nullable": true,
            "type": "string"
          },
          "sn": {
            "nullable": true,
            "type": "string"
          },
          "type": {
            "$ref": "#/components/schemas/ObjectTypeTag"
          },
          "uuid": {
            "type": "string",
            "format": "uuid"
          }
        },
        "required": [
          "account",
          "login",
          "type",
          "uuid"
        ],
        "additionalProperties": true
      },
      "UuidToNameBody": {
        "description": "Body of the deprecated `POST /getName`.",
        "type": "object",
        "properties": {
          "uuid": {
            "description": "Single uuid or array of uuids. Kept as `String` here because the body may carry either a bare string or a JSON array of strings; UUID parsing happens in the service layer so we can surface a clean 400 for malformed input.",
            "allOf": [
              {
                "$ref": "#/components/schemas/StringOrVec"
              }
            ]
          }
        },
        "required": [
          "uuid"
        ]
      }
    },
    "responses": {
      "Error": {
        "description": "Error",
        "content": {
          "application/json": {
            "schema": {
              "$ref": "#/components/schemas/Error"
            }
          }
        }
      }
    }
  },
  "tags": [
    {
      "name": "aws-sigv4"
    },
    {
      "name": "iam"
    },
    {
      "name": "lookup"
    },
    {
      "name": "lookup-deprecated"
    },
    {
      "name": "sts"
    }
  ]
}
